AUTHOR.txt
CHANGES.txt
LICENSE.txt
MANIFEST.in
README.txt
bootstrap.py
buildout.cfg
setup.cfg
setup.py
version.txt
src/koansys/__init__.py
src/koansys.recipe.elasticsearch.egg-info/PKG-INFO
src/koansys.recipe.elasticsearch.egg-info/SOURCES.txt
src/koansys.recipe.elasticsearch.egg-info/dependency_links.txt
src/koansys.recipe.elasticsearch.egg-info/entry_points.txt
src/koansys.recipe.elasticsearch.egg-info/namespace_packages.txt
src/koansys.recipe.elasticsearch.egg-info/not-zip-safe
src/koansys.recipe.elasticsearch.egg-info/requires.txt
src/koansys.recipe.elasticsearch.egg-info/top_level.txt
src/koansys/recipe/__init__.py
src/koansys/recipe/elasticsearch/README.txt
src/koansys/recipe/elasticsearch/__init__.py
src/koansys/recipe/elasticsearch/tests/__init__.py
src/koansys/recipe/elasticsearch/tests/test_doc.py