Metadata-Version: 1.0
Name: koansys.recipe.elasticsearch
Version: 1.0.2
Summary: ZC Buildout recipe for setting up elasticsearch.
Home-page: http://pypi.python.org/pypi/koansys.recipe.elasticsearch
Author: Koansys, LLC
Author-email: info@koansys.com
License: LGPL 3
Keywords: elasticsearch zc.buildout recipe
Platform: UNKNOWN
Classifier: Development Status :: 5 - Production/Stable
Classifier: Framework :: Buildout
Classifier: Intended Audience :: Developers
Classifier: License :: OSI Approved :: GNU Library or Lesser General Public License (LGPL)
Classifier: Topic :: Software Development :: Build Tools
Classifier: Topic :: Software Development :: Libraries :: Python Modules
